kirin/__init__.py
kirin/exception.py
kirin/graph.py
kirin/idtable.py
kirin/prelude.py
kirin/py.typed
kirin/registry.py
kirin/source.py
kirin/symbol_table.py
kirin/types.py
kirin/worklist.py
kirin/analysis/__init__.py
kirin/analysis/callgraph.py
kirin/analysis/cfg.py
kirin/analysis/forward.py
kirin/analysis/const/__init__.py
kirin/analysis/const/_visitor.py
kirin/analysis/const/_visitor.pyi
kirin/analysis/const/lattice.py
kirin/analysis/const/prop.py
kirin/analysis/typeinfer/__init__.py
kirin/analysis/typeinfer/analysis.py
kirin/analysis/typeinfer/solve.py
kirin/decl/__init__.py
kirin/decl/base.py
kirin/decl/camel2snake.py
kirin/decl/info.py
kirin/decl/scan_fields.py
kirin/decl/verify.py
kirin/decl/emit/__init__.py
kirin/decl/emit/_create_fn.py
kirin/decl/emit/_set_new_attribute.py
kirin/decl/emit/check.py
kirin/decl/emit/check_type.py
kirin/decl/emit/dialect.py
kirin/decl/emit/init.py
kirin/decl/emit/name.py
kirin/decl/emit/property.py
kirin/decl/emit/repr.py
kirin/decl/emit/traits.py
kirin/dialects/__init__.py
kirin/dialects/debug.py
kirin/dialects/eltype.py
kirin/dialects/module.py
kirin/dialects/ssacfg.py
kirin/dialects/cf/__init__.py
kirin/dialects/cf/abstract.py
kirin/dialects/cf/constprop.py
kirin/dialects/cf/dialect.py
kirin/dialects/cf/interp.py
kirin/dialects/cf/stmts.py
kirin/dialects/func/__init__.py
kirin/dialects/func/_dialect.py
kirin/dialects/func/_julia.py
kirin/dialects/func/attrs.py
kirin/dialects/func/constprop.py
kirin/dialects/func/interp.py
kirin/dialects/func/stmts.py
kirin/dialects/func/typeinfer.py
kirin/dialects/func/rewrite/__init__.py
kirin/dialects/func/rewrite/closurefield.py
kirin/dialects/func/rewrite/lambdalifting.py
kirin/dialects/ilist/__init__.py
kirin/dialects/ilist/_dialect.py
kirin/dialects/ilist/_julia.py
kirin/dialects/ilist/_wrapper.py
kirin/dialects/ilist/constprop.py
kirin/dialects/ilist/interp.py
kirin/dialects/ilist/lowering.py
kirin/dialects/ilist/passes.py
kirin/dialects/ilist/runtime.py
kirin/dialects/ilist/stmts.py
kirin_toolchain-0.22.6.dist-info/METADATA
kirin_toolchain-0.22.6.dist-info/WHEEL
kirin_toolchain-0.22.6.dist-info/licenses/LICENSE
kirin_toolchain-0.22.6.dist-info/RECORD
