Metadata-Version: 2.4
Name: kirin-toolchain
Version: 0.22.6
Summary: The Kirin Toolchain for building compilers and interpreters.
Author-email: Roger-luo <rluo@quera.com>
License-File: LICENSE
Requires-Python: >=3.10
Requires-Dist: beartype>=0.17.2
Requires-Dist: rich>=13.7.1
Requires-Dist: typing-extensions>=4.11.0
Provides-Extra: vmath
Requires-Dist: numpy>1.26.0; extra == 'vmath'
Requires-Dist: scipy>=1.15.3; extra == 'vmath'
